renault/__init__.py
renault/excpetion.py
renault/renault.py
renault_api_lite-0.8.2.dist-info/LICENSE
renault_api_lite-0.8.2.dist-info/METADATA
renault_api_lite-0.8.2.dist-info/WHEEL
renault_api_lite-0.8.2.dist-info/top_level.txt
renault_api_lite-0.8.2.dist-info/RECORD
