Metadata-Version: 2.1
Name: renault-api-lite
Version: 0.8.2
Summary: Lightweight Python API for querying status info for a variety of Renault vehicle models
Home-page: https://github.com/bkogler/renault-api-lite
Author: Bernhard Kogler
Author-email: bernhard.kogler@supersonnig.org
License: MIT
Keywords: Renault Z.E. ZOE Twingo Megane Kangoo Electric vehicle EV status API
Classifier: Development Status :: 5 - Production/Stable
Classifier: Programming Language :: Python :: 3
Classifier: License :: OSI Approved :: MIT License
Classifier: Operating System :: OS Independent
Requires-Python: >=3.10
License-File: LICENSE
Requires-Dist: renault-api (>=0.1.13)
